PytrackX/__init__.py
PytrackX/config.py
PytrackX/detection.py
PytrackX/module.py
PytrackX/track.py
PytrackX-0.7.dist-info/LICENSE
PytrackX-0.7.dist-info/METADATA
PytrackX-0.7.dist-info/WHEEL
PytrackX-0.7.dist-info/top_level.txt
PytrackX-0.7.dist-info/RECORD
