Metadata-Version: 2.1
Name: PytrackX
Version: 0.7
Summary: A general python framework for visual object tracking.
Home-page: https://github.com/swetha4444/PyTrackX
Author: Sriram Kannan, Swetha Saseendran
Author-email: swethasaseendran4@gmail.com
License: MIT
Download-URL: https://github.com/swetha4444/PyTrackX/archive/refs/tags/0.7.tar.gz
Project-URL: Bug Tracker, https://github.com/swetha4444/PyTrackX/issues
Keywords: yolo,mediapipe,object detection,object tracking
Platform: UNKNOWN
Classifier: Programming Language :: Python :: 3
Classifier: License :: OSI Approved :: MIT License
Classifier: Operating System :: OS Independent
License-File: LICENSE
Requires-Dist: numpy (>=1.11)
Requires-Dist: matplotlib (>=1.5)
Requires-Dist: pandas (>=1)
Requires-Dist: opencv-python (>=4.4.0.44)
Requires-Dist: scipy (>=1.5.4)
Requires-Dist: mediapipe (>=0.8.4.2)
